orman_news_reader/__init__.py
orman_news_reader/__main__.py
orman_news_reader/google_rss_extractor.py
orman_news_reader/html_generator.py
orman_news_reader/reader_mode.py
orman_news_reader/selenium_redirect_tracker.py
orman_news_reader-0.3.4.dist-info/METADATA
orman_news_reader-0.3.4.dist-info/WHEEL
orman_news_reader-0.3.4.dist-info/entry_points.txt
orman_news_reader-0.3.4.dist-info/RECORD
