Metadata-Version: 2.1
Name: orman-news-reader
Version: 0.3.4
Summary: Extracts the main content from webpages and generates clean, reader-friendly HTML
Home-page: https://github.com/ormanisreal/orman-news-reader
License: MIT
Keywords: web,reader,readability,html,content-extraction,google-news
Author: Quine Orman
Author-email: ormanisreal@gmail.com
Requires-Python: >=3.10,<4.0
Classifier: Development Status :: 4 - Beta
Classifier: Intended Audience :: Developers
Classifier: License :: OSI Approved :: MIT License
Classifier: Programming Language :: Python :: 3
Classifier: Programming Language :: Python :: 3.10
Classifier: Programming Language :: Python :: 3.11
Classifier: Programming Language :: Python :: 3.12
Classifier: Programming Language :: Python :: 3.8
Classifier: Programming Language :: Python :: 3.9
Classifier: Topic :: Internet :: WWW/HTTP
Classifier: Topic :: Text Processing :: Markup :: HTML
Requires-Dist: beautifulsoup4 (==4.12.2)
Requires-Dist: feedparser (>=6.0.11,<7.0.0)
Requires-Dist: lxml (>=4.9.3,<5.0.0)
Requires-Dist: lxml-html-clean (>=0.1.0,<0.2.0)
Requires-Dist: pillow (==10.1.0)
Requires-Dist: pyvirtualdisplay (>=3.0,<4.0)
Requires-Dist: readability-lxml (==0.8.1)
Requires-Dist: requests (==2.31.0)
Requires-Dist: selenium (>=4.29.0,<5.0.0)
Project-URL: Repository, https://github.com/ormanisreal/orman-news-reader
